{
    "icPrebidRubiconDisplay": [
        {
            "apps": [
                "futhead",
                "gamepedia",
                "mobile-wiki",
                "muthead",
                "oasis"
            ],
            "regions": [
                "XX"
            ],
            "value": true
        }
    ],
    "wgAdDriverUapRestriction": 1,
    "icLABradorTest": [
        {
            "apps": [
                "f2",
                "futhead",
                "gamepedia",
                "mobile-wiki",
                "muthead",
                "oasis"
            ],
            "regions": [
                "PL"
            ],
            "sampling": 35.0,
            "samplingCache": true,
            "value": true
        }
    ],
    "wgAdDriverTestCommunities": [
        "cdm_gamepedia",
        "project43"
    ],
    "icPrebidOpenX": [
        {
            "apps": [
                "futhead",
                "gamepedia",
                "mobile-wiki",
                "muthead",
                "oasis"
            ],
            "regions": [
                "XX"
            ],
            "value": true
        }
    ],
    "icTestCommunities": [
        {
            "apps": [
                "gamepedia"
            ],
            "regions": [
                "XX"
            ],
            "value": [
                "cdm_gamepedia"
            ]
        }
    ],
    "wgAdDriverUapCountries": [
        "XX"
    ],
    "icTaxonomyAdTags": [
        {
            "apps": [
                "gamepedia"
            ],
            "regions": [
                "XX"
            ],
            "value": true
        }
    ],
    "icPrebidIndexExchange": [
        {
            "apps": [
                "futhead",
                "gamepedia",
                "mobile-wiki",
                "muthead",
                "oasis"
            ],
            "regions": [
                "XX"
            ],
            "value": true
        }
    ],
    "icUapRestriction": [
        {
            "apps": [
                "gamepedia"
            ],
            "regions": [
                "XX"
            ],
            "value": 1
        }
    ],
    "icPostmessageTracking": [
        {
            "apps": [
                "f2",
                "gamepedia",
                "mobile-wiki",
                "oasis"
            ],
            "regions": [
                "XX"
            ],
            "value": true
        }
    ],
    "icBidsTracking": [
        {
            "apps": [
                "futhead",
                "gamepedia",
                "mobile-wiki",
                "muthead",
                "oasis"
            ],
            "regions": [
                "CZ"
            ],
            "value": true
        }
    ],
    "icPrebidCriteo": [
        {
            "apps": [
                "futhead",
                "gamepedia",
                "mobile-wiki",
                "muthead",
                "oasis"
            ],
            "regions": [
                "XX"
            ],
            "value": true
        }
    ],
    "icPrebidVersion": [
        {
            "apps": [
                "futhead",
                "gamepedia",
                "mobile-wiki",
                "muthead",
                "oasis"
            ],
            "regions": [
                "US-CA",
                "US-NY"
            ],
            "sampling": 100.0,
            "value": "https://origin-images.wikia.com/fandom-ae-assets/prebid.js/v3.2.0/20200114.min.js"
        },
        {
            "apps": [
                "futhead",
                "gamepedia",
                "mobile-wiki",
                "muthead",
                "oasis"
            ],
            "regions": [
                "GB",
                "UK",
                "US"
            ],
            "value": "https://origin-images.wikia.com/fandom-ae-assets/prebid.js/v2.44.2/20200110.min.js"
        },
        {
            "apps": [
                "futhead",
                "gamepedia",
                "mobile-wiki",
                "muthead",
                "oasis"
            ],
            "regions": [
                "XX"
            ],
            "value": "https://origin-images.wikia.com/fandom-ae-assets/prebid.js/v3.2.0/20200114.min.js"
        }
    ],
    "icA9Bidder": [
        {
            "apps": [
                "futhead",
                "gamepedia",
                "mobile-wiki",
                "muthead",
                "oasis"
            ],
            "regions": [
                "XX"
            ],
            "value": true
        }
    ],
    "icPrebidTriplelift": [
        {
            "apps": [
                "futhead",
                "gamepedia",
                "mobile-wiki",
                "muthead",
                "oasis"
            ],
            "regions": [
                "XX"
            ],
            "value": true
        }
    ],
    "wgAdDriverDelayTimeout": 2000,
    "icConfiant": [
        {
            "apps": [
                "gamepedia"
            ],
            "devices": [
                "smartphone"
            ],
            "regions": [
                "US"
            ],
            "value": true
        }
    ],
    "icPrebidAppNexus": [
        {
            "apps": [
                "futhead",
                "gamepedia",
                "mobile-wiki",
                "muthead",
                "oasis"
            ],
            "regions": [
                "XX"
            ],
            "value": true
        }
    ],
    "icPrebidPubmatic": [
        {
            "apps": [
                "futhead",
                "gamepedia",
                "mobile-wiki",
                "muthead",
                "oasis"
            ],
            "regions": [
                "XX"
            ],
            "value": true
        }
    ],
    "icBTRec": [
        {
            "apps": [
                "gamepedia"
            ],
            "devices": [
                "desktop"
            ],
            "regions": [
                "XX"
            ],
            "value": true
        }
    ],
    "icPrebidSendAllBids": [
        {
            "apps": [
                "futhead",
                "gamepedia",
                "mobile-wiki",
                "muthead",
                "oasis"
            ],
            "regions": [
                "PL"
            ],
            "sampling": 5.0,
            "value": true
        },
        {
            "apps": [
                "futhead",
                "gamepedia",
                "mobile-wiki",
                "muthead",
                "oasis"
            ],
            "regions": [
                "CZ"
            ],
            "sampling": 100.0,
            "value": true
        }
    ],
    "icPrebid": [
        {
            "apps": [
                "futhead",
                "gamepedia",
                "mobile-wiki",
                "muthead",
                "oasis"
            ],
            "regions": [
                "XX"
            ],
            "value": true
        }
    ],
    "icPrebidNobid": [
        {
            "apps": [
                "futhead",
                "gamepedia",
                "mobile-wiki",
                "muthead",
                "oasis"
            ],
            "regions": [
                "XX"
            ],
            "value": true
        }
    ],
    "icBabDetection": [
        {
            "apps": [
                "f2",
                "futhead",
                "gamepedia",
                "mobile-wiki",
                "muthead",
                "oasis"
            ],
            "regions": [
                "XX"
            ],
            "value": true
        }
    ],
    "icPermutive": [
        {
            "apps": [
                "f2",
                "gamepedia",
                "mobile-wiki",
                "oasis"
            ],
            "regions": [
                "GB",
                "PL",
                "UK",
                "US"
            ],
            "value": true
        }
    ],
    "icDurationMedia": [
        {
            "apps": [
                "gamepedia"
            ],
            "regions": [
                "XX"
            ],
            "value": true
        }
    ],
    "icA9Deals": [
        {
            "apps": [
                "futhead",
                "gamepedia",
                "mobile-wiki",
                "muthead",
                "oasis"
            ],
            "regions": [
                "XX"
            ],
            "value": true
        }
    ],
    "wgAdDriverLABradorTestCountries": [
        "PL/35-cached"
    ],
    "icAdEngineDelay": [
        {
            "apps": [
                "f2",
                "futhead",
                "gamepedia",
                "mobile-wiki",
                "muthead",
                "oasis"
            ],
            "regions": [
                "XX"
            ],
            "value": 2000
        }
    ],
    "icOutstreamSlot": [
        {
            "apps": [
                "gamepedia"
            ],
            "regions": [
                "XX"
            ],
            "value": false
        }
    ]
}